endymion/__init__.py
endymion/box.py
endymion/checksums.py
endymion/policy.py
endymion/urlutil.py
endymion-1.4.1.dist-info/DESCRIPTION.rst
endymion-1.4.1.dist-info/METADATA
endymion-1.4.1.dist-info/RECORD
endymion-1.4.1.dist-info/WHEEL
endymion-1.4.1.dist-info/entry_points.txt
endymion-1.4.1.dist-info/metadata.json
endymion-1.4.1.dist-info/top_level.txt
