Metadata-Version: 2.0
Name: endymion
Version: 1.4.1
Summary: A small tool to check the link validity of external Vagrant boxes on Atlas
Home-page: https://github.com/lpancescu/endymion
Author: Laurențiu Păncescu
Author-email: laurentiu@laurentiupancescu.com
License: MIT
Keywords: vagrant atlas
Platform: UNKNOWN
Classifier: Development Status :: 4 - Beta
Classifier: Intended Audience :: Developers
Classifier: Topic :: Utilities
Classifier: License :: OSI Approved :: MIT License
Classifier: Programming Language :: Python :: 2
Classifier: Programming Language :: Python :: 2.7
Classifier: Programming Language :: Python :: 3
Classifier: Programming Language :: Python :: 3.5
